ri_excel/__init__.py
ri_excel/excel_reader.py
ri_excel/excel_writer.py
ri_excel/model/__init__.py
ri_excel/model/cell_config.py
ri_excel/model/excel_config.py
ri_excel/model/field_config.py
ri_excel/model/reference_config.py
ri_excel/model/result_config.py
ri_excel/model/sheet_config.py
ri_excel/service/__init__.py
ri_excel/service/reference_service.py
ri_excel/service/result_service.py
ri_excel/service/sheet_service.py
ri_excel/util/__init__.py
ri_excel/util/util.py
ri_excel-0.1.0.dist-info/licenses/LICENSE
ri_excel-0.1.0.dist-info/METADATA
ri_excel-0.1.0.dist-info/WHEEL
ri_excel-0.1.0.dist-info/top_level.txt
ri_excel-0.1.0.dist-info/RECORD
