Metadata-Version: 2.4
Name: ri-excel
Version: 0.1.0
Summary: Utilities for excel management.
Author-email: Ravetta Stefano <s.ravetta94@gmail.com>
License-Expression: Apache-2.0
Project-URL: Homepage, https://github.com/ShikaruAriki/ri-excel
Classifier: Programming Language :: Python :: 3
Classifier: Programming Language :: Python :: 3.10
Classifier: Operating System :: OS Independent
Requires-Python: >=3.10.12
License-File: LICENSE
Requires-Dist: build==1.2.2
Requires-Dist: dataclass-wizard==0.35.0
Requires-Dist: deepdiff==8.5.0
Requires-Dist: openpyxl==3.1.5
Requires-Dist: pytest==8.4.0
Requires-Dist: setuptools==80.9.0
Requires-Dist: tox==4.26.0
Requires-Dist: twine==6.1.0
Requires-Dist: wheel==0.46.1
Dynamic: license-file
